[
  {
    "x_min": 700.9732666015625,
    "y_min": 600.4054565429688,
    "x_max": 805.4188232421875,
    "y_max": 698.94921875,
    "text": "PINGOLF: Score-2 or better on three holes"
  },
  {
    "x_min": 804.757568359375,
    "y_min": 601.3276977539062,
    "x_max": 908.8546142578125,
    "y_max": 699.0986328125,
    "text": "HYPER CONTENDERWn 3 ights in a row on Hyper difficulty on default ring settings"
  },
  {
    "x_min": 908.2545776367188,
    "y_min": 600.0927124023438,
    "x_max": 1012.38818359375,
    "y_max": 699.1455688476562,
    "text": "PORGY Collect 3fuel tanks"
  },
  {
    "x_min": 1012.0162353515625,
    "y_min": 599.65576171875,
    "x_max": 1116.4776611328125,
    "y_max": 698.7652587890625,
    "text": "CYBEROWLS: Clear Hong Kong only destroying Road Toad"
  },
  {
    "x_min": 1115.6827392578125,
    "y_min": 599.3380737304688,
    "x_max": 1220.6787109375,
    "y_max": 698.1295166015625,
    "text": "Find an egg in 10 different games"
  },
  {
    "x_min": 701.3629150390625,
    "y_min": 698.4720458984375,
    "x_max": 805.295166015625,
    "y_max": 794.24755859375,
    "text": "RAKSHASA: Score 25,000"
  },
  {
    "x_min": 804.92724609375,
    "y_min": 698.9185180664062,
    "x_max": 907.7946166992188,
    "y_max": 794.1336669921875,
    "text": "Collect 4 gold disks"
  },
  {
    "x_min": 907.4432983398438,
    "y_min": 698.9528198242188,
    "x_max": 1012.7252197265625,
    "y_max": 793.7034301757812,
    "text": "NINPEK:Eat 5 sandwiches"
  },
  {
    "x_min": 1012.1795654296875,
    "y_min": 698.6229858398438,
    "x_max": 1117.452392578125,
    "y_max": 793.74462890625,
    "text": "WARPTANK: SLIM-TANK allowed,clear Riot and Soft Sectors"
  },
  {
    "x_min": 1116.804931640625,
    "y_min": 697.5462646484375,
    "x_max": 1220.5352783203125,
    "y_max": 794.0223388671875,
    "text": "HYPER CONTENDER:Win 4 fights in a row without rematches on default ring settings"
  },
  {
    "x_min": 700.813232421875,
    "y_min": 794.1923217773438,
    "x_max": 805.505859375,
    "y_max": 888.77001953125,
    "text": "ONION DELIVERY: Have 99 seconds remaining"
  },
  {
    "x_min": 805.0968017578125,
    "y_min": 794.131591796875,
    "x_max": 907.327392578125,
    "y_max": 889.0383911132812,
    "text": "MORTOLIL: In one run, defeat at least 2 enemies with each player class"
  },
  {
    "x_min": 906.9662475585938,
    "y_min": 793.6151123046875,
    "x_max": 1012.6907958984375,
    "y_max": 889.2947998046875,
    "text": "PILOTQUEST: Return a ship part to the crash site"
  },
  {
    "x_min": 1012.3104858398438,
    "y_min": 793.6925048828125,
    "x_max": 1117.423583984375,
    "y_max": 889.0311279296875,
    "text": "Collect 10 gifts for the garden"
  },
  {
    "x_min": 1116.6605224609375,
    "y_min": 793.9340209960938,
    "x_max": 1220.209716796875,
    "y_max": 888.4183349609375,
    "text": "ROCKONI ISLAND:Beat Initial Encounter wlo upgrading at the cave"
  },
  {
    "x_min": 701.2747802734375,
    "y_min": 888.6851196289062,
    "x_max": 805.4173583984375,
    "y_max": 984.0374145507812,
    "text": "OTPARTYCollect the Gift in 4 of these 0 games: Campanella 1/2/3,Planet Zoldath Plot Quest, The Big Bell Race"
  },
  {
    "x_min": 805.00537109375,
    "y_min": 888.9195556640625,
    "x_max": 907.4638671875,
    "y_max": 983.9493408203125,
    "text": "GRIMSTONE: Collect the money from the burned house"
  },
  {
    "x_min": 907.147705078125,
    "y_min": 889.1967163085938,
    "x_max": 1012.4053344726562,
    "y_max": 984.0865478515625,
    "text": "HOTFOOT Get 3 blowouts in one toumament"
  },
  {
    "x_min": 1011.9656982421875,
    "y_min": 889.0004272460938,
    "x_max": 1117.2281494140625,
    "y_max": 984.1550903320312,
    "text": "BUG HUNTER Get4kills in one job by stomping on bugs"
  },
  {
    "x_min": 1116.8773193359375,
    "y_min": 888.0452880859375,
    "x_max": 1220.3944091796875,
    "y_max": 983.866943359375,
    "text": "BLOCK KOALA: WORM-1234 allowed;clear 9 story levels"
  },
  {
    "x_min": 701.2159423828125,
    "y_min": 983.8094482421875,
    "x_max": 804.9984130859375,
    "y_max": 1079.449462890625,
    "text": "LORDS OF DISKONIA: Win the first mission"
  },
  {
    "x_min": 804.650146484375,
    "y_min": 983.9215087890625,
    "x_max": 907.5322875976562,
    "y_max": 1079.23681640625,
    "text": "OVERBOLD: Clear a round with maximum stakes"
  },
  {
    "x_min": 907.52392578125,
    "y_min": 983.888427734375,
    "x_max": 1012.2022094726562,
    "y_max": 1079.4781494140625,
    "text": "Beat4levels in 5 different games"
  },
  {
    "x_min": 1011.947265625,
    "y_min": 983.9381713867188,
    "x_max": 1117.015869140625,
    "y_max": 1079.2703857421875,
    "text": "HYPER CONTENDER Beat Draft Mode(Default settings)"
  },
  {
    "x_min": 1116.5579833984375,
    "y_min": 983.6116943359375,
    "x_max": 1220.74755859375,
    "y_max": 1079.5172119140625,
    "text": "CAMPANELLA 2:Clear Moire Woodsll or RinkII"
  }
]